README.md
setup.cfg
setup.py
spx/__init__.py
spx/smartplug.py
spx/tool.py
spx.egg-info/PKG-INFO
spx.egg-info/SOURCES.txt
spx.egg-info/dependency_links.txt
spx.egg-info/entry_points.txt
spx.egg-info/requires.txt
spx.egg-info/top_level.txt