Metadata-Version: 1.0
Name: spx
Version: 0.3.0
Summary: Unofficial Python Library for Edimax Smartplugs SP-2101W and SP-1101W
Home-page: https://github.com/tback/spx
Author: Till Backhaus
Author-email: till@backha.us
License: MIT
Platform: UNKNOWN
